argo/workflows/dsl/__about__.py
argo/workflows/dsl/__init__.py
argo/workflows/dsl/_arguments.py
argo/workflows/dsl/_base.py
argo/workflows/dsl/_cronworkflow.py
argo/workflows/dsl/_inputs.py
argo/workflows/dsl/_outputs.py
argo/workflows/dsl/_utils.py
argo/workflows/dsl/_workflow.py
argo/workflows/dsl/_workflow_template.py
argo/workflows/dsl/tasks.py
argo/workflows/dsl/templates.py
argo_workflows_dsl-0.4.0.dist-info/LICENSE
argo_workflows_dsl-0.4.0.dist-info/METADATA
argo_workflows_dsl-0.4.0.dist-info/WHEEL
argo_workflows_dsl-0.4.0.dist-info/top_level.txt
argo_workflows_dsl-0.4.0.dist-info/RECORD
