Metadata-Version: 2.1
Name: argo-workflows-dsl
Version: 0.4.0
Summary: DSL for Argo Workflows
Home-page: https://github.com/CermakM/argo-python-dsl
Author: Yudi Xue, Marek Cermak
Author-email: binarycrayon@gmail.com, macermak@redhat.com
License: Apache Software License
Platform: UNKNOWN
Classifier: Development Status :: 2 - Pre-Alpha
Classifier: Intended Audience :: Developers
Classifier: Intended Audience :: Information Technology
Classifier: License :: OSI Approved :: Apache Software License
Classifier: Operating System :: OS Independent
Classifier: Programming Language :: Python :: 3.6
Classifier: Programming Language :: Python :: 3.7
Classifier: Topic :: Software Development
Classifier: Topic :: Utilities
Requires-Dist: argo-workflows (==4.0.1)
Requires-Dist: inflection
Requires-Dist: pyyaml
